{
    "ListObject": [
        {
            "UserName": "ISC.phuongnv35",
            "SessionID": "ndejqc0nznbprkgejdnumjqm",
            "DeviceIMEI": "3547561034821061",
            "Token": "LIhzK!f9Bwiz!$AO)7(DyMkgtcPknE)tEG%U-4W(-Qw6t1h2IewHadg)pAGzv$V(y6v4)xOLl-Eiiv59$fcIZ8Sts)w)ypUD#zI4Gv3cQlobZ(i#MO3PlMq7nCLAAPf$wAn0nA3Su-!5T9Tui23j3Fk0JSREj2cAGtwYczYMdlnlT2nw0ikPd$Krh5rV1y09p!zsM$S0erGRk-gZwmWASMoKiE8oIDcw2v%bC$j5Q1347!HiYSqOc0qcVoJIEwsb"
        }
    ],
    "Error": null,
    "ErrorCode": 0
}